LICENSE
kitsu_extended/__init__.py
kitsu_extended/client.py
kitsu_extended/errors.py
kitsu_extended/models.py
kitsu_extended/py.typed
kitsu.py_extended-1.0.4.dist-info/LICENSE
kitsu.py_extended-1.0.4.dist-info/WHEEL
kitsu.py_extended-1.0.4.dist-info/METADATA
kitsu.py_extended-1.0.4.dist-info/RECORD
