Metadata-Version: 2.1
Name: kitsu.py-extended
Version: 1.0.4
Summary: kitsu.py_extened is an asynchronous API wrapper for Kitsu written in Python. (Extend kitsu.py)
Home-page: https://github.com/dymattic/kitsu.py_extended/
License: MIT
Keywords: kitsu,async kitsu,kitsu.py,kitsu api wrapper
Author: Dymattic
Author-email: dymattic@naise.io
Maintainer: Dymattic
Maintainer-email: dymattic@naise.io
Requires-Python: >=3.8,<4.0
Classifier: Intended Audience :: Developers
Classifier: License :: OSI Approved :: MIT License
Classifier: Natural Language :: English
Classifier: Operating System :: OS Independent
Classifier: Programming Language :: Python :: 3
Classifier: Programming Language :: Python :: 3.10
Classifier: Programming Language :: Python :: 3.8
Classifier: Programming Language :: Python :: 3.9
Classifier: Topic :: Games/Entertainment
Classifier: Topic :: Internet
Classifier: Topic :: Software Development :: Libraries
Classifier: Topic :: Software Development :: Libraries :: Python Modules
Classifier: Topic :: Utilities
Classifier: Typing :: Typed
Requires-Dist: aiohttp (>=3.7.4,<4.0.0)
Requires-Dist: python-dateutil (>=2.8.2,<3.0.0)
Project-URL: Bug Tracker, https://github.com/dymattic/kitsu.py_extended/issues
Project-URL: Changelog, https://github.com/dymattic/kitsu.py_extended/blob/master/CHANGELOG.md
Project-URL: Repository, https://github.com/dymattic/kitsu.py_extended/
